odoo/addons/purchase_stock_secondary_unit/README.rst
odoo/addons/purchase_stock_secondary_unit/__init__.py
odoo/addons/purchase_stock_secondary_unit/__manifest__.py
odoo/addons/purchase_stock_secondary_unit/i18n/es.po
odoo/addons/purchase_stock_secondary_unit/i18n/purchase_stock_secondary_unit.pot
odoo/addons/purchase_stock_secondary_unit/models/__init__.py
odoo/addons/purchase_stock_secondary_unit/models/purchase_order_line.py
odoo/addons/purchase_stock_secondary_unit/models/stock_move.py
odoo/addons/purchase_stock_secondary_unit/readme/CONTRIBUTORS.rst
odoo/addons/purchase_stock_secondary_unit/readme/DESCRIPTION.rst
odoo/addons/purchase_stock_secondary_unit/readme/USAGE.rst
odoo/addons/purchase_stock_secondary_unit/static/description/icon.png
odoo/addons/purchase_stock_secondary_unit/static/description/index.html
odoo/addons/purchase_stock_secondary_unit/tests/__init__.py
odoo/addons/purchase_stock_secondary_unit/tests/test_purchase_stock_secondary_unit.py
odoo13_addon_purchase_stock_secondary_unit-13.0.1.0.2.dist-info/METADATA
odoo13_addon_purchase_stock_secondary_unit-13.0.1.0.2.dist-info/WHEEL
odoo13_addon_purchase_stock_secondary_unit-13.0.1.0.2.dist-info/top_level.txt
odoo13_addon_purchase_stock_secondary_unit-13.0.1.0.2.dist-info/RECORD
